kloppy_spark/__init__.py
kloppy_spark/pipeline.py
kloppy_spark/stage.py
kloppy_spark/sinks/__init__.py
kloppy_spark/sinks/show_dataframe.py
kloppy_spark/sources/__init__.py
kloppy_spark/sources/dataset_source.py
kloppy_spark/sources/datasets.py
kloppy_spark/stages/__init__.py
kloppy_spark/stages/coordinates_transform.py
kloppy_spark/stages/passes_into_zone.py
kloppy_spark/stages/plot_passes.py
kloppy_spark/stages/score.py
kloppy_spark/stages/sequences.py
kloppy_spark/tests/__init__.py
kloppy_spark/utils/__init__.py
kloppy_spark/utils/graph.py
kloppy_spark/utils/kloppy_helpers.py
kloppy_spark/utils/pitch.py
kloppy_spark/utils/zone.py
kloppy_spark-0.0.3.dist-info/LICENSE
kloppy_spark-0.0.3.dist-info/METADATA
kloppy_spark-0.0.3.dist-info/WHEEL
kloppy_spark-0.0.3.dist-info/top_level.txt
kloppy_spark-0.0.3.dist-info/RECORD
