Metadata-Version: 2.1
Name: kloppy-spark
Version: 0.0.3
Summary: Spark Tools to work with Kloppy
Home-page: https://deepsports.io
Author: Felix Schmdit
Author-email: info@deepsports.io
License: BSD
Platform: UNKNOWN
Classifier: Intended Audience :: Developers
Classifier: Intended Audience :: Science/Research
Classifier: Programming Language :: Python :: 3
Classifier: Programming Language :: Python :: 3.6
Classifier: Programming Language :: Python :: 3.7
Classifier: Programming Language :: Python :: 3.8
Classifier: License :: OSI Approved
Classifier: Topic :: Scientific/Engineering
Requires-Dist: kloppy (>=1.5.1)
Requires-Dist: pyspark (>=3.0.1)
Requires-Dist: graphframes (>=0.6)
Requires-Dist: numpy (>=1.19.4)
Requires-Dist: matplotlib (>=3.3.3)
Provides-Extra: development
Requires-Dist: pre-commit ; extra == 'development'
Provides-Extra: test
Requires-Dist: pytest ; extra == 'test'
Requires-Dist: pandas (>=1.0.0) ; extra == 'test'
